{
  "id": "Sistema/Criação de Personagem/Habilidades/Essências Elementais/Essências Elementais de Água/Essência Congelante/Essência Congelante Experiente",
  "path": "Sistema/Criação de Personagem/Habilidades/Essências Elementais/Essências Elementais de Água/Essência Congelante/Essência Congelante Experiente.md",
  "basename": "Essência Congelante Experiente",
  "type": "Habilidade",
  "subtype": null,
  "grupo": null,
  "frontmatter": {
    "alias": null,
    "categoria": "Habilidade",
    "subcategoria": null,
    "elemento": "Água",
    "dg-publish": true,
    "Elementos_de_Regra": [
      "Complementar Magias.Lista [[Cristalização Gélida]]"
    ]
  },
  "inlineFields": {
    "up": "[[Habilidades]]",
    "prev": "",
    "next": "",
    "classe": "",
    "rank": "[[Experiente]]",
    "resumo": "\"experiente [[Cristalização Gélida]]\""
  },
  "ruleElements": [
    {
      "raw": "Complementar Magias.Lista [[Cristalização Gélida]]",
      "parsed": [
        {
          "sourceNote": "Essência Congelante Experiente",
          "occurrenceIndex": 0,
          "scope": [],
          "condition": {
            "kind": "none"
          },
          "channel": "editable",
          "action": {
            "kind": "complementar",
            "targetRaw": "Magias.Lista",
            "valueRaw": "[[Cristalização Gélida]]"
          },
          "raw": "Complementar Magias.Lista [[Cristalização Gélida]]",
          "provenance": []
        }
      ]
    }
  ],
  "links": [
    {
      "target": "Habilidades",
      "kind": "wikilink"
    },
    {
      "target": "Experiente",
      "kind": "wikilink"
    },
    {
      "target": "Cristalização Gélida",
      "kind": "wikilink"
    }
  ],
  "images": [],
  "headings": [
    {
      "level": 4,
      "text": "`= this.file.name`"
    }
  ],
  "body": "%%\nup:: [[Habilidades]]\nprev:: \nnext:: \n\nclasse:: \nrank:: [[Experiente]]\n\nresumo:: \"experiente [[Cristalização Gélida]]\"\n%%\n#### `= this.file.name`\n* experiente [[Cristalização Gélida]]\n\n```autosheet-rules\n```\n"
}
